meshmemory/__init__.py
meshmemory/audit.py
meshmemory/clarifier.py
meshmemory/cmb.py
meshmemory/events.py
meshmemory/memory_evolution.py
meshmemory/svaf_api.py
meshmemory/svaf_fusion.py
meshmemory/vee.py
meshmemory-0.1.0.dist-info/licenses/LICENSE.md
meshmemory-0.1.0.dist-info/METADATA
meshmemory-0.1.0.dist-info/WHEEL
meshmemory-0.1.0.dist-info/top_level.txt
meshmemory-0.1.0.dist-info/RECORD
