Metadata-Version: 2.4
Name: meshmemory
Version: 0.1.0
Summary: Composable, event-driven cognitive memory protocol for AI and multi-agent systems—enabling structured onboarding, symbolic–vector fusion, remix, and full audit trails for semantic continuity and explainable intelligence.
Author-email: Consenix Labs Ltd <info@consenix.com>
Project-URL: Homepage, https://meshmemory.io
Project-URL: Documentation, https://docs.meshmemory.io
Project-URL: Repository, https://github.com/meshmemory/meshmemory-sdk
Classifier: Programming Language :: Python :: 3
Classifier: Operating System :: OS Independent
Requires-Python: >=3.8
License-File: LICENSE.md
Requires-Dist: numpy>=1.20
Dynamic: license-file
